BatchParse/__init__.py
BatchParse/main.py
BatchParse/util/__init__.py
BatchParse/util/info.py
BatchParse/util/settings.py
BatchParse/util/splitting.py
BatchParse-0.0.7.dist-info/LICENSE
BatchParse-0.0.7.dist-info/METADATA
BatchParse-0.0.7.dist-info/WHEEL
BatchParse-0.0.7.dist-info/top_level.txt
BatchParse-0.0.7.dist-info/RECORD
